crema/__init__.py
crema/confidence.py
crema/crema.py
crema/dataset.py
crema/params.py
crema/qvalues.py
crema/utils.py
crema/parsers/__init__.py
crema/parsers/comet.py
crema/parsers/msamanda.py
crema/parsers/msfragger.py
crema/parsers/msgf.py
crema/parsers/mztab.py
crema/parsers/pepxml.py
crema/parsers/tide.py
crema/parsers/txt.py
crema/writers/__init__.py
crema/writers/txt.py
tests/__init__.py
tests/conftest.py
tests/system_tests/__init__.py
tests/system_tests/test_cli.py
tests/system_tests/test_crux_tdc.py
tests/unit_tests/__init__.py
tests/unit_tests/test_confidence.py
tests/unit_tests/test_dataset.py
tests/unit_tests/test_parsers.py
tests/unit_tests/test_qvalues.py
crema_ms-0.0.10.dist-info/LICENSE
crema_ms-0.0.10.dist-info/METADATA
crema_ms-0.0.10.dist-info/WHEEL
crema_ms-0.0.10.dist-info/entry_points.txt
crema_ms-0.0.10.dist-info/top_level.txt
crema_ms-0.0.10.dist-info/RECORD
