Metadata-Version: 2.1
Name: crema-ms
Version: 0.0.10
Summary: Confidence estimation for proteomics experiments
Home-page: https://github.com/noble-lab/crema
Author: Andy Lin
Author-email: linandy@uw.edu
License: Apache 2.0
Project-URL: Documentation, https://crema-ms.readthedocs.io
Project-URL: Bug Tracker, https://github.com/noble-lab/crema/issues
Classifier: Programming Language :: Python :: 3
Classifier: License :: OSI Approved :: Apache Software License
Classifier: Operating System :: OS Independent
Classifier: Topic :: Scientific/Engineering :: Bio-Informatics
Requires-Python: >=3.6
License-File: LICENSE
Requires-Dist: numpy >=1.18.1
Requires-Dist: pandas >=1.3.0
Requires-Dist: numba >=0.48.0
Requires-Dist: pyteomics >=4.4.2
Requires-Dist: lxml >=4.6.3
Provides-Extra: dev
Requires-Dist: pre-commit >=2.7.1 ; extra == 'dev'
Requires-Dist: black >=20.8b1 ; extra == 'dev'
Provides-Extra: docs
Requires-Dist: numpydoc >=1.0.0 ; extra == 'docs'
Requires-Dist: sphinx-argparse >=0.2.5 ; extra == 'docs'
Requires-Dist: sphinx-rtd-theme >=0.5.0 ; extra == 'docs'
Requires-Dist: nbsphinx >=0.7.1 ; extra == 'docs'
Requires-Dist: ipykernel >=5.3.0 ; extra == 'docs'
Requires-Dist: recommonmark >=0.5.0 ; extra == 'docs'
